{
	"width": 9,
	"height": 9,
	"tiles": {
		"walls": [
			{
				"type": 2,
				"row": 0,
				"col": 3,
				"size": 3
			}, {
				"type": 1,
				"size": -3
			}, {
				"type": 2,
				"size": 3
			}, {
				"type": 1,
				"size": 3
			}, {
				"type": 2,
				"size": 3
			}, {
				"type": 1,
				"size": 3
			}, {
				"type": 2,
				"size": -3
			}, {
				"type": 1,
				"size": 3
			}, {
				"type": 2,
				"size": -3
			}, {
				"type": 1,
				"size": -3
			}, {
				"type": 2,
				"size": -3
			}, {
				"type": 1,
				"size": -3
			}
		],
		"lines": [
			{
				"type": 1,
				"row": 4,
				"col": 1,
				"size": 1
			}
		],
		"stars": [
			{
				"row": 1,
				"col": 4
			}, {
				"row": 4,
				"col": 7
			}, {
				"row": 7,
				"col": 4
			}
		],
		"reflectors": [
			{
				"type": 4,
				"row": 4,
				"col": 4,
				"opt": {
					"rotatable": true,
					"hideable": false
				}
			}
		],
		"traps": [
			{
				"type": 2,
				"row": 4,
				"col": 9
			}
		]
	}
}