{"width":12,"height":7,"tiles":{"lines":[{"type":1,"size":1,"row":5,"col":1}],"walls":[{"type":1,"size":12,"row":0,"col":0},{"type":2,"size":7},{"type":1,"size":-12},{"type":2,"size":-3},{"type":1,"size":5},{"type":2,"size":-1},{"type":1,"size":-5},{"type":2,"size":-3},{"type":1,"size":1,"row":3,"col":8},{"type":2,"size":1},{"type":1,"size":-1},{"type":2,"size":-1}],"traps":[{"type":1,"row":0,"col":6},{"type":1,"row":7,"col":6}],"stars":[{"row":1,"col":1}],"spirals":[],"reflectors":[{"type":2,"row":1,"col":6,"opt":{"rotatable":true}},{"type":3,"row":5,"col":10},{"type":4,"row":1,"col":10}],"bricks":[]}}